dotgit/__init__.py
dotgit/__main__.py
dotgit/args.py
dotgit/calc_ops.py
dotgit/checks.py
dotgit/enums.py
dotgit/file_ops.py
dotgit/flists.py
dotgit/git.py
dotgit/info.py
dotgit/plugin.py
dotgit/plugins/__init__.py
dotgit/plugins/encrypt.py
dotgit/plugins/plain.py
dotgit-2.2.9.data/scripts/dotgit.sh
dotgit-2.2.9.dist-info/LICENSE
dotgit-2.2.9.dist-info/METADATA
dotgit-2.2.9.dist-info/WHEEL
dotgit-2.2.9.dist-info/entry_points.txt
dotgit-2.2.9.dist-info/top_level.txt
dotgit-2.2.9.dist-info/RECORD
