Metadata-Version: 2.1
Name: dotgit
Version: 2.2.9
Summary: A comprehensive solution to managing your dotfiles
Home-page: https://github.com/kobus-v-schoor/dotgit
Author: Kobus van Schoor
Author-email: v.schoor.kobus@gmail.com
License: GNU General Public License v2 (GPLv2)
Project-URL: Documentation, https://dotgit.readthedocs.io
Platform: UNKNOWN
Classifier: Development Status :: 5 - Production/Stable
Classifier: Programming Language :: Python :: 3
Classifier: License :: OSI Approved :: GNU General Public License v2 (GPLv2)
Classifier: Operating System :: POSIX
Classifier: Operating System :: MacOS
Classifier: Topic :: Utilities
Requires-Python: >=3.6
